setup.py
pytextsearch/__init__.py
pytextsearch/boyer_moore.py
pytextsearch/kmp.py
pytextsearch/rabin_karp.py
pytextsearch.egg-info/PKG-INFO
pytextsearch.egg-info/SOURCES.txt
pytextsearch.egg-info/dependency_links.txt
pytextsearch.egg-info/top_level.txt